axilent/__init__.py
axilent/cocotb_handler.py
axilent/comms.py
axilent/config.py
axilent/dicts.py
axilent/handlers.py
axilent/test_utils.py
axilent/version.py
axilent/examples/axi_adder.py
axilent/vhdl/axi_adder.core
axilent/vhdl/axi_adder.vhd
axilent/vhdl/axi_adder_assertions.vhd
axilent/vhdl/axi_adder_pkg.vhd
axilent/vhdl/axi_adder_unwrapped.vhd
axilent/vhdl/axi_utils.core
axilent/vhdl/axi_utils.vhd
axilent-0.1.8.dist-info/LICENSE
axilent-0.1.8.dist-info/METADATA
axilent-0.1.8.dist-info/WHEEL
axilent-0.1.8.dist-info/top_level.txt
axilent-0.1.8.dist-info/RECORD
