Metadata-Version: 2.1
Name: axilent
Version: 0.1.8
Summary: Tools for describing a sequence of Axi4Lite commands.
Home-page: https://github.com/benreynwar/axilent
Author: Ben Reynwar
Author-email: ben@reynwar.net
License: MIT
Keywords: VHDL,hdl,rtl,FPGA,ASIC,Xilinx,Altera
Platform: UNKNOWN
Requires-Dist: jinja2 (>=2.8)
Requires-Dist: pytest
Requires-Dist: slvcodec (>=0.4.10)
